mcplaystats/__init__.py
mcplaystats/player.py
mcplaystats/statistics.py
McPlayHDStats-1.0.1.dist-info/LICENSE
McPlayHDStats-1.0.1.dist-info/METADATA
McPlayHDStats-1.0.1.dist-info/WHEEL
McPlayHDStats-1.0.1.dist-info/top_level.txt
McPlayHDStats-1.0.1.dist-info/RECORD
