Metadata-Version: 2.1
Name: McPlayHDStats
Version: 1.0.1
Summary: Unofficial API Wrapper for McPlayHD API
Home-page: UNKNOWN
Author: Mythological
Author-email: UNKNOWN
License: MIT
Platform: UNKNOWN
